ginormal/__init__.py
ginormal/dgin.py
ginormal/dtgin.py
ginormal/rgin.py
ginormal/rtgin.py
ginormal/utils/F0gin.py
ginormal/utils/__init__.py
ginormal/utils/dgin1.py
ginormal/utils/mshift.py
ginormal/utils/pbdam.py
ginormal/utils/rtgin1.py
ginormal-0.0.13.dist-info/LICENSE.md
ginormal-0.0.13.dist-info/METADATA
ginormal-0.0.13.dist-info/WHEEL
ginormal-0.0.13.dist-info/top_level.txt
ginormal-0.0.13.dist-info/RECORD
