Metadata-Version: 2.1
Name: ginormal
Version: 0.0.13
Summary: Generalized Inverse Normal distribution density and generation
Author-email: Santiago Montoya-Blandón <Santiago.Montoya-Blandon@glasgow.ac.uk>, Cheng Ding <cheng.ding.emory@gmail.com>, Juan Estrada <jjestra@emory.edu>, Zhilang Xia <zhilang.xia@glasgow.ac.uk>
Maintainer-email: Santiago Montoya-Blandón <Santiago.Montoya-Blandon@glasgow.ac.uk>
Project-URL: Homepage, https://github.com/smonto2/ginormal
Project-URL: Bug tracking, https://github.com/smonto2/ginormal/issues
Keywords: statistics,distribution,generalized inverse normal,random variable generation
Classifier: Programming Language :: Python :: 3.8
Classifier: License :: OSI Approved :: MIT License
Classifier: Operating System :: OS Independent
Requires-Python: >=3.8
License-File: LICENSE.md
Requires-Dist: numpy
Requires-Dist: scipy
Requires-Dist: cardano-method
